geojson_pydantic/__init__.py
geojson_pydantic/base.py
geojson_pydantic/features.py
geojson_pydantic/geometries.py
geojson_pydantic/py.typed
geojson_pydantic/types.py
geojson_pydantic-2.0.0.dist-info/licenses/LICENSE
geojson_pydantic-2.0.0.dist-info/WHEEL
geojson_pydantic-2.0.0.dist-info/METADATA
geojson_pydantic-2.0.0.dist-info/RECORD
