Metadata-Version: 2.4
Name: geojson-pydantic
Version: 2.0.0
Summary: Pydantic data models for the GeoJSON spec.
Keywords: geojson,Pydantic
Author-email: Drew Bollinger <drew@developmentseed.org>
Requires-Python: >=3.9
Classifier: Intended Audience :: Information Technology
Classifier: Intended Audience :: Science/Research
Classifier: License :: OSI Approved :: MIT License
Classifier: Programming Language :: Python :: 3.9
Classifier: Programming Language :: Python :: 3.10
Classifier: Programming Language :: Python :: 3.11
Classifier: Programming Language :: Python :: 3.12
Classifier: Programming Language :: Python :: 3.13
Classifier: Topic :: Scientific/Engineering :: GIS
Classifier: Typing :: Typed
License-File: LICENSE
Requires-Dist: pydantic~=2.0
Requires-Dist: pre-commit ; extra == "dev"
Requires-Dist: bump-my-version ; extra == "dev"
Requires-Dist: mkdocs ; extra == "docs"
Requires-Dist: mkdocs-material ; extra == "docs"
Requires-Dist: pygments ; extra == "docs"
Requires-Dist: pytest ; extra == "test"
Requires-Dist: pytest-cov ; extra == "test"
Requires-Dist: shapely ; extra == "test"
Project-URL: Source, https://github.com/developmentseed/geojson-pydantic
Provides-Extra: dev
Provides-Extra: docs
Provides-Extra: test
